Metadata-Version: 2.1
Name: onyeka-gauss-dist
Version: 0.1
Summary: Gaussian distributions
